pixify/__init__.py
pixify/cli.py
pixify/helpers/Option.py
pixify/helpers/__init__.py
pixify/helpers/file.py
pixify/services/__init__.py
pixify/services/converter.py
pixify-0.0.1.dist-info/METADATA
pixify-0.0.1.dist-info/WHEEL
pixify-0.0.1.dist-info/entry_points.txt
pixify-0.0.1.dist-info/top_level.txt
pixify-0.0.1.dist-info/RECORD
