Metadata-Version: 2.4
Name: pixify
Version: 0.0.1
Summary: A simple CLI image converter built with Pillow and Typer.
Home-page: https://github.com/AryaTjiutanto/pixify
Author: Arya Tjiutanto
Author-email: Arya Tjiutanto <aryatjiutanto.dev@gmail.com>
License: MIT
Project-URL: Homepage, https://github.com/AryaTjiutanto/pixify
Keywords: cli,image,converter,pillow,typer
Classifier: Programming Language :: Python :: 3
Classifier: License :: OSI Approved :: MIT License
Classifier: Operating System :: OS Independent
Classifier: Environment :: Console
Classifier: Topic :: Multimedia :: Graphics :: Graphics Conversion
Classifier: Intended Audience :: Developers
Classifier: Development Status :: 3 - Alpha
Requires-Python: >=3.7
Requires-Dist: pillow
Requires-Dist: typer
Requires-Dist: yaspin
Dynamic: author
Dynamic: home-page
Dynamic: requires-python
